<?xml version="1.0" encoding="UTF-8"?><oai_dc:dc xmlns:dc="http://purl.org/dc/elements/1.1/" xmlns:xsi="http://www.w3.org/2001/XMLSchema-instance" xsi:schemaLocation="http://www.openarchives.org/OAI/2.0/oai_dc/ http://www.openarchives.org/OAI/2.0/oai_dc.xsd" xmlns:oai_dc="http://www.openarchives.org/OAI/2.0/oai_dc/">
    <dc:contributor>Lalana del Castillo, Carlos</dc:contributor>
    <dc:creator>Igea García, Alberto</dc:creator>
    <dc:date>2019</dc:date>
    <dc:description>La prodigalidad es una figura del Derecho Civil que se encuentra regulada en su mayoría en la LEC de 7 de Enero del 2000 y en el Código Civil, pero es la jurisprudencia y la doctrina los que se encargan de completar la figura y establecer sus requisitos, características y reglas.&lt;br /&gt;Existen opiniones muy diversas en la doctrina sobre distintos aspectos de la prodigalidad. Además, tampoco hay una coordinación total entre la regulación estatal y la de la Comunidad Autónoma de Aragón sobre distintos supuestos, como he explicado en el trabajo.&lt;br /&gt;Es una figura no muy utilizada actualmente pero pienso que debería mantenerse y que puede ser útil si se aplica a los casos adecuados ya que es un elemento de protección de la situación económica de la familia con derecho de alimentos.&lt;br /&gt;&lt;br /&gt;</dc:description>
    <dc:identifier>http://zaguan.unizar.es/record/90162</dc:identifier>
    <dc:language>spa</dc:language>
    <dc:publisher>Universidad de Zaragoza; Departamento de Derecho Privado; Área de Derecho Civil</dc:publisher>
    <dc:relation>http://zaguan.unizar.es/record/90162/files/TAZ-TFG-2019-2788.pdf</dc:relation>
    <dc:rights>http://creativecommons.org/licenses/by-nc-sa/3.0/</dc:rights>
    <dc:subject>Graduado en Derecho</dc:subject>
    <dc:title>La prodigalidad</dc:title>
    <dc:type>TAZ-TFG</dc:type>
    <dc:title xml:lang="en">The prodigality</dc:title>
</oai_dc:dc>
