<?xml version="1.0" encoding="UTF-8"?><oai_dc:dc xmlns:dc="http://purl.org/dc/elements/1.1/" xmlns:xsi="http://www.w3.org/2001/XMLSchema-instance" xsi:schemaLocation="http://www.openarchives.org/OAI/2.0/oai_dc/ http://www.openarchives.org/OAI/2.0/oai_dc.xsd" xmlns:oai_dc="http://www.openarchives.org/OAI/2.0/oai_dc/">
    <dc:contributor>Lacalzada De Mateo, María José</dc:contributor>
    <dc:creator>Vicien Andres, Rebeca</dc:creator>
    <dc:date>2016</dc:date>
    <dc:description>El tema del presente proyecto se centra en la elaboración de un Programa de intervención de Rehabilitación Psicosocial orientado a reforzar las habilidades sociales destinadas a personas que padecen trastornos mentales graves donde su objetivo principal es: Mejorar la calidad de vida de las personas con enfermedad mental grave en su entorno social cotidiano en España partiendo de la Reforma psiquiátrica, haciendo una mirada política social fundamentada en los derechos humanos fundamentales.</dc:description>
    <dc:identifier>http://zaguan.unizar.es/record/57249</dc:identifier>
    <dc:language>spa</dc:language>
    <dc:publisher>Universidad de Zaragoza; Departamento de Psicología y Sociología; Área de Trabajo Social y Servicios Sociales</dc:publisher>
    <dc:relation>http://zaguan.unizar.es/record/57249/files/TAZ-TFG-2016-1583.pdf</dc:relation>
    <dc:rights>http://creativecommons.org/licenses/by-nc-sa/3.0/</dc:rights>
    <dc:subject>Graduado en Trabajo Social</dc:subject>
    <dc:title>VIVIR – SANA – MENTE Programa de Rehabilitación Psicosocial para mejorar la calidad de vida en las personas con enfermedad mental grave.</dc:title>
    <dc:type>TAZ-TFG</dc:type>
    <dc:title xml:lang="en">HEALTHY LIVING Psychosocial Rehabilitation Program to improve the quality of life of people with serious mental disease.</dc:title>
</oai_dc:dc>
