<?xml version="1.0" encoding="UTF-8"?><oai_dc:dc xmlns:dc="http://purl.org/dc/elements/1.1/" xmlns:xsi="http://www.w3.org/2001/XMLSchema-instance" xsi:schemaLocation="http://www.openarchives.org/OAI/2.0/oai_dc/ http://www.openarchives.org/OAI/2.0/oai_dc.xsd" xmlns:oai_dc="http://www.openarchives.org/OAI/2.0/oai_dc/">
    <dc:contributor>Olmo Vicen, Nuria del</dc:contributor>
    <dc:contributor>Boira Sarto, Santiago</dc:contributor>
    <dc:creator>Esbert García, Joaquín</dc:creator>
    <dc:date>2014</dc:date>
    <dc:description>Este trabajo de sistematización de un caso real, pretende analizar y conocer la incidencia y el significado que tiene para la víctima de violencia de género o de pareja, la relación de ayuda y el vínculo profesional establecido por los profesionales de atención primaria ubicados en los Centros de Servicios Sociales Comarcales</dc:description>
    <dc:identifier>http://zaguan.unizar.es/record/31391</dc:identifier>
    <dc:language>spa</dc:language>
    <dc:publisher>Universidad de Zaragoza; Departamento de Psicología y Sociología; Área de Trabajo Social y Servicios Sociales</dc:publisher>
    <dc:relation>http://zaguan.unizar.es/record/31391/files/TAZ-TFG-2014-2360.pdf</dc:relation>
    <dc:rights>http://creativecommons.org/licenses/by-nc-sa/3.0/</dc:rights>
    <dc:subject>Graduado en Trabajo Social</dc:subject>
    <dc:title>La importancia de la relación de ayuda y el vínculo entre el trabajador/a social y la víctima de violencia de pareja o de género</dc:title>
    <dc:type>TAZ-TFG</dc:type>
</oai_dc:dc>
